codex_mcp_async/__init__.py
codex_mcp_async/__main__.py
codex_mcp_async/server.py
codex_mcp_async-0.2.1.dist-info/licenses/LICENSE
codex_mcp_async-0.2.1.dist-info/METADATA
codex_mcp_async-0.2.1.dist-info/WHEEL
codex_mcp_async-0.2.1.dist-info/entry_points.txt
codex_mcp_async-0.2.1.dist-info/top_level.txt
codex_mcp_async-0.2.1.dist-info/RECORD
