Metadata-Version: 2.4
Name: codex-mcp-async
Version: 0.2.1
Summary: Asynchronous MCP wrapper for OpenAI Codex CLI with context filtering
Author: jeanchristophe13v
Maintainer: jeanchristophe13v
License-Expression: MIT
Project-URL: Homepage, https://github.com/jeanchristophe13v/codex-mcp-async
Project-URL: Repository, https://github.com/jeanchristophe13v/codex-mcp-async.git
Project-URL: Issues, https://github.com/jeanchristophe13v/codex-mcp-async/issues
Keywords: mcp,openai,codex,claude,gpt-5,async
Classifier: Development Status :: 4 - Beta
Classifier: Intended Audience :: Developers
Classifier: Programming Language :: Python :: 3
Classifier: Programming Language :: Python :: 3.8
Classifier: Programming Language :: Python :: 3.9
Classifier: Programming Language :: Python :: 3.10
Classifier: Programming Language :: Python :: 3.11
Classifier: Programming Language :: Python :: 3.12
Classifier: Topic :: Software Development :: Libraries :: Python Modules
Classifier: Topic :: Scientific/Engineering :: Artificial Intelligence
Requires-Python: >=3.8
License-File: LICENSE
Provides-Extra: dev
Requires-Dist: pytest>=6.0; extra == "dev"
Requires-Dist: black>=22.0; extra == "dev"
Requires-Dist: isort>=5.0; extra == "dev"
Requires-Dist: flake8>=4.0; extra == "dev"
Dynamic: license-file
